LinkMLFormbuilder/__init__.py
LinkMLFormbuilder/bootstrap.css
LinkMLFormbuilder/constants.py
LinkMLFormbuilder/formbuilder.py
LinkMLFormbuilder/slot_code_generators.py
LinkMLFormbuilder/styles.css
LinkMLFormbuilder/utils.py
linkmlformbuilder-1.0.0.dist-info/METADATA
linkmlformbuilder-1.0.0.dist-info/WHEEL
linkmlformbuilder-1.0.0.dist-info/entry_points.txt
linkmlformbuilder-1.0.0.dist-info/licenses/LICENSE
linkmlformbuilder-1.0.0.dist-info/RECORD
