Metadata-Version: 2.3
Name: LinkMLFormbuilder
Version: 1.0.0
Summary: Build forms from LinkML. Export to HTML or (basic) PDF
Project-URL: Homepage, https://github.com/AmsterdamUMC/LinkMLFormBuilder#
Project-URL: Issues, https://github.com/AmsterdamUMC/LinkMLFormBuilder/issues
Author: N. van Brummelen
License-Expression: GPL-3.0-only
License-File: LICENSE
Classifier: License :: OSI Approved :: GNU General Public License v3 (GPLv3)
Classifier: Operating System :: OS Independent
Classifier: Programming Language :: Python :: 3
Requires-Python: >=3
Requires-Dist: pdfkit
Requires-Dist: pyyaml
